charliehr/__init__.py
charliehr/api_client.py
charliehr_client-1.0.3.dist-info/licenses/LICENSE
charliehr_client-1.0.3.dist-info/METADATA
charliehr_client-1.0.3.dist-info/WHEEL
charliehr_client-1.0.3.dist-info/top_level.txt
charliehr_client-1.0.3.dist-info/RECORD
