Metadata-Version: 2.4
Name: charliehr-client
Version: 1.0.3
Summary: A lightweight, robust Python client for interacting with the CharlieHR API.
Home-page: https://github.com/scottmurray2789/charliehr-client
Author: Scott Murray
Author-email: scottmurray2789@gmail.com
Classifier: Programming Language :: Python :: 3
Classifier: License :: OSI Approved :: MIT License
Classifier: Operating System :: OS Independent
Requires-Python: >=3.10
License-File: LICENSE
Requires-Dist: requests>=2.32.3
Requires-Dist: urllib3>=2.4.0
Dynamic: author
Dynamic: author-email
Dynamic: classifier
Dynamic: description
Dynamic: description-content-type
Dynamic: home-page
Dynamic: license-file
Dynamic: requires-dist
Dynamic: requires-python
Dynamic: summary
